mammos/__init__.py
mammos/_fetch_examples.py
mammos/py.typed
mammos-0.11.2.dist-info/METADATA
mammos-0.11.2.dist-info/WHEEL
mammos-0.11.2.dist-info/entry_points.txt
mammos-0.11.2.dist-info/licenses/LICENSE
mammos-0.11.2.dist-info/RECORD
