Metadata-Version: 2.4
Name: mammos
Version: 0.11.2
Summary: A multiphyscis simulation suite for magnetic materials.
Project-URL: Homepage, https://MaMMoS-project.github.io
Project-URL: Documentation, https://mammos-project.github.io/mammos
Project-URL: Repository, https://github.com/MaMMoS-project/mammos
Project-URL: Issues, https://github.com/MaMMoS-project/mammos/issues
Project-URL: Changelog, https://mammos-project.github.io/mammos/changelog
Author: Andrea Petrocchi, Swapneel Amit Pathak, Samuel Holt, Martin Lang, Hans Fangohr
License-Expression: MIT
License-File: LICENSE
Classifier: Intended Audience :: Developers
Classifier: Intended Audience :: Education
Classifier: Intended Audience :: Science/Research
Classifier: Programming Language :: Python :: 3 :: Only
Classifier: Topic :: Scientific/Engineering :: Physics
Requires-Python: >=3.11
Requires-Dist: mammos-ai==0.2.0
Requires-Dist: mammos-analysis==0.4.0
Requires-Dist: mammos-dft==0.4.1
Requires-Dist: mammos-entity==0.11.1
Requires-Dist: mammos-mumag==0.10.1
Requires-Dist: mammos-spindynamics==0.3.1
Requires-Dist: mammos-units==0.3.2
